{"0.0.4": ["Lars Kunze", "l.kunze@cs.bham.ac.uk"], "0.0.1": ["Lars Kunze", "l.kunze@cs.bham.ac.uk"], "0.0.3": ["Lars Kunze", "l.kunze@cs.bham.ac.uk"], "0.0.2": ["Lars Kunze", "l.kunze@cs.bham.ac.uk"], "0.1.0": ["Lars Kunze", "l.kunze@cs.bham.ac.uk"], "0.1.1": ["Lars Kunze", "l.kunze@cs.bham.ac.uk"], "0.1.2": ["Lars Kunze", "l.kunze@cs.bham.ac.uk"], "0.1.3": ["Lars Kunze", "l.kunze@cs.bham.ac.uk"], "0.1.4": ["Lars Kunze", "l.kunze@cs.bham.ac.uk"], "0.1.5": ["Lars Kunze", "l.kunze@cs.bham.ac.uk"], "0.1.6": ["Lars Kunze", "l.kunze@cs.bham.ac.uk"], "0.1.7": ["Lars Kunze", "l.kunze@cs.bham.ac.uk"]}